{
  "generator-jhipster": {
    "authenticationType": "jwt",
    "cacheProvider": "no",
    "clientFramework": "angularX",
    "serverPort": "8080",
    "serviceDiscoveryType": "eureka",
    "skipUserManagement": false,
    "baseName": "Gateway",
    "buildTool": "gradle",
    "databaseType": "sql",
    "devDatabaseType": "h2Memory",
    "enableHibernateCache": false,
    "enableSwaggerCodegen": false,
    "enableTranslation": true,
    "jhiPrefix": "jhi",
    "languages": ["en", "fr"],
    "messageBroker": false,
    "nativeLanguage": "en",
    "prodDatabaseType": "mysql",
    "searchEngine": false,
    "skipClient": true,
    "testFrameworks": [],
    "websocket": false,
    "applicationType": "gateway",
    "packageName": "com.ps.banking.retail",
    "packageFolder": "com/ps/banking/retail",
    "jhipsterVersion": "6.9.1",
    "creationTimestamp": 1595773500035,
    "skipServer": false,
    "clientPackageManager": "npm",
    "clientTheme": "none",
    "clientThemeVariant": "",
    "useSass": true,
    "jwtSecretKey": "YjM5NGUzMDcwYWQyYjAxNDE3OTMxYTczY2RmNmQwZDI5MGZmYTI5ODlkNmFmNWFkNGRkNzE0ZDQ4NDUyYjdmNWNlYzE2YWUzZDY3MjRkZTU4OGE2NzY2YmU1YmY3ZmIyNjdkYWIxMDA0MzNiMWQyMzEzYzFmNDg1NzUzOGZjNjU=",
    "embeddableLaunchScript": false,
    "entitySuffix": "",
    "dtoSuffix": "DTO",
    "otherModules": [],
    "blueprints": []
  },
  "entities": []
}
